{
"meta":{"test_sets":[],"test_metrics":[],"learn_metrics":[{"best_value":"Min","name":"RMSE"}],"launch_mode":"Train","parameters":"","iteration_count":100,"learn_sets":["learn"],"name":"experiment"},
"iterations":[
{"learn":[64.05721752],"iteration":0,"passed_time":0.001260416667,"remaining_time":0.12478125},
{"learn":[60.55906493],"iteration":1,"passed_time":0.001961583333,"remaining_time":0.09611758333},
{"learn":[57.23125275],"iteration":2,"passed_time":0.0027595,"remaining_time":0.08922383333},
{"learn":[54.91291086],"iteration":3,"passed_time":0.003476833333,"remaining_time":0.083444},
{"learn":[52.22855164],"iteration":4,"passed_time":0.004205041667,"remaining_time":0.07989579167},
{"learn":[49.96686243],"iteration":5,"passed_time":0.004943833333,"remaining_time":0.07745338889},
{"learn":[48.32330028],"iteration":6,"passed_time":0.005588375,"remaining_time":0.07424555357},
{"learn":[46.47257955],"iteration":7,"passed_time":0.006278833333,"remaining_time":0.07220658333},
{"learn":[44.67484885],"iteration":8,"passed_time":0.006910125,"remaining_time":0.06986904167},
{"learn":[43.11977771],"iteration":9,"passed_time":0.0075965,"remaining_time":0.0683685},
{"learn":[41.79634973],"iteration":10,"passed_time":0.0082365,"remaining_time":0.06664077273},
{"learn":[40.45020105],"iteration":11,"passed_time":0.008847,"remaining_time":0.064878},
{"learn":[39.24203044],"iteration":12,"passed_time":0.00947625,"remaining_time":0.06341798077},
{"learn":[38.26102792],"iteration":13,"passed_time":0.01021991667,"remaining_time":0.0627794881},
{"learn":[37.46861878],"iteration":14,"passed_time":0.01090204167,"remaining_time":0.06177823611},
{"learn":[37.07640973],"iteration":15,"passed_time":0.012303875,"remaining_time":0.06459534375},
{"learn":[36.09345753],"iteration":16,"passed_time":0.0137405,"remaining_time":0.06708597059},
{"learn":[35.30595935],"iteration":17,"passed_time":0.01447245833,"remaining_time":0.06593008796},
{"learn":[34.57947574],"iteration":18,"passed_time":0.01536508333,"remaining_time":0.06550377632},
{"learn":[34.07602848],"iteration":19,"passed_time":0.016342,"remaining_time":0.065368},
{"learn":[33.74275232],"iteration":20,"passed_time":0.01733179167,"remaining_time":0.0652005496},
{"learn":[33.34252218],"iteration":21,"passed_time":0.01825245833,"remaining_time":0.06471326136},
{"learn":[33.00588017],"iteration":22,"passed_time":0.01914054167,"remaining_time":0.06407920471},
{"learn":[32.74776001],"iteration":23,"passed_time":0.02002995833,"remaining_time":0.06342820139},
{"learn":[32.42781549],"iteration":24,"passed_time":0.02083775,"remaining_time":0.06251325},
{"learn":[31.99563324],"iteration":25,"passed_time":0.021824625,"remaining_time":0.06211624038},
{"learn":[31.46775216],"iteration":26,"passed_time":0.02270745833,"remaining_time":0.0613942392},
{"learn":[31.08244377],"iteration":27,"passed_time":0.02357754167,"remaining_time":0.06062796429},
{"learn":[30.86622129],"iteration":28,"passed_time":0.02502783333,"remaining_time":0.06127504023},
{"learn":[30.42608185],"iteration":29,"passed_time":0.02599875,"remaining_time":0.06066375},
{"learn":[29.9570186],"iteration":30,"passed_time":0.02708204167,"remaining_time":0.06027938306},
{"learn":[29.71630766],"iteration":31,"passed_time":0.02802058333,"remaining_time":0.05954373958},
{"learn":[29.51903713],"iteration":32,"passed_time":0.02898254167,"remaining_time":0.05884334217},
{"learn":[29.13676935],"iteration":33,"passed_time":0.02983041667,"remaining_time":0.05790610294},
{"learn":[28.8018493],"iteration":34,"passed_time":0.03081625,"remaining_time":0.05723017857},
{"learn":[28.35320616],"iteration":35,"passed_time":0.03179579167,"remaining_time":0.05652585185},
{"learn":[27.83174121],"iteration":36,"passed_time":0.03269416667,"remaining_time":0.05566844595},
{"learn":[27.37540757],"iteration":37,"passed_time":0.03371683333,"remaining_time":0.05501167544},
{"learn":[27.17636693],"iteration":38,"passed_time":0.03454041667,"remaining_time":0.05402475427},
{"learn":[26.99397688],"iteration":39,"passed_time":0.03541158333,"remaining_time":0.053117375},
{"learn":[26.79248472],"iteration":40,"passed_time":0.03634795833,"remaining_time":0.05230559858},
{"learn":[26.44064664],"iteration":41,"passed_time":0.03718825,"remaining_time":0.05135520238},
{"learn":[26.18220656],"iteration":42,"passed_time":0.03809929167,"remaining_time":0.05050371221},
{"learn":[26.04137952],"iteration":43,"passed_time":0.0390355,"remaining_time":0.04968154545},
{"learn":[25.40689486],"iteration":44,"passed_time":0.03999020833,"remaining_time":0.0488769213},
{"learn":[25.09674745],"iteration":45,"passed_time":0.04090225,"remaining_time":0.04801568478},
{"learn":[24.89092128],"iteration":46,"passed_time":0.04182454167,"remaining_time":0.04716384486},
{"learn":[24.73226479],"iteration":47,"passed_time":0.04293075,"remaining_time":0.0465083125},
{"learn":[24.62193617],"iteration":48,"passed_time":0.04384408333,"remaining_time":0.04563363776},
{"learn":[24.33004026],"iteration":49,"passed_time":0.04489733333,"remaining_time":0.04489733333},
{"learn":[24.18182071],"iteration":50,"passed_time":0.04585795833,"remaining_time":0.04405960703},
{"learn":[23.78106129],"iteration":51,"passed_time":0.0468075,"remaining_time":0.04320692308},
{"learn":[23.35117357],"iteration":52,"passed_time":0.04782458333,"remaining_time":0.04241047956},
{"learn":[23.05701076],"iteration":53,"passed_time":0.049227625,"remaining_time":0.04193464352},
{"learn":[22.96340068],"iteration":54,"passed_time":0.050120375,"remaining_time":0.04100757955},
{"learn":[22.86567429],"iteration":55,"passed_time":0.05106279167,"remaining_time":0.04012076488},
{"learn":[22.56521824],"iteration":56,"passed_time":0.05207595833,"remaining_time":0.03928537208},
{"learn":[22.34244144],"iteration":57,"passed_time":0.05292133333,"remaining_time":0.03832234483},
{"learn":[22.06871653],"iteration":58,"passed_time":0.05384533333,"remaining_time":0.0374179435},
{"learn":[21.93953482],"iteration":59,"passed_time":0.05473816667,"remaining_time":0.03649211111},
{"learn":[21.83398057],"iteration":60,"passed_time":0.055579125,"remaining_time":0.03553419467},
{"learn":[21.70853179],"iteration":61,"passed_time":0.05661445833,"remaining_time":0.03469918414},
{"learn":[21.39245866],"iteration":62,"passed_time":0.057538125,"remaining_time":0.03379223214},
{"learn":[21.27951875],"iteration":63,"passed_time":0.05858625,"remaining_time":0.03295476563},
{"learn":[21.03575506],"iteration":64,"passed_time":0.05945229167,"remaining_time":0.03201277244},
{"learn":[20.57906906],"iteration":65,"passed_time":0.06029004167,"remaining_time":0.03105850631},
{"learn":[20.36293863],"iteration":66,"passed_time":0.06112075,"remaining_time":0.03010425},
{"learn":[20.05737792],"iteration":67,"passed_time":0.062041,"remaining_time":0.02919576471},
{"learn":[19.80644447],"iteration":68,"passed_time":0.06309575,"remaining_time":0.02834736594},
{"learn":[19.7297845],"iteration":69,"passed_time":0.06417941667,"remaining_time":0.02750546429},
{"learn":[19.56738316],"iteration":70,"passed_time":0.06503979167,"remaining_time":0.02656554871},
{"learn":[19.34574357],"iteration":71,"passed_time":0.06664445833,"remaining_time":0.02591728935},
{"learn":[19.27407895],"iteration":72,"passed_time":0.067618625,"remaining_time":0.02500962842},
{"learn":[19.01268017],"iteration":73,"passed_time":0.068619375,"remaining_time":0.02410951014},
{"learn":[18.93240234],"iteration":74,"passed_time":0.069527125,"remaining_time":0.02317570833},
{"learn":[18.79871155],"iteration":75,"passed_time":0.070467,"remaining_time":0.02225273684},
{"learn":[18.59860313],"iteration":76,"passed_time":0.07152904167,"remaining_time":0.02136581764},
{"learn":[18.41213072],"iteration":77,"passed_time":0.0724435,"remaining_time":0.02043278205},
{"learn":[18.23504209],"iteration":78,"passed_time":0.073461,"remaining_time":0.01952760759},
{"learn":[18.17382959],"iteration":79,"passed_time":0.07512079167,"remaining_time":0.01878019792},
{"learn":[18.12664898],"iteration":80,"passed_time":0.07600070833,"remaining_time":0.01782732665},
{"learn":[18.07818085],"iteration":81,"passed_time":0.0769195,"remaining_time":0.01688476829},
{"learn":[17.9205028],"iteration":82,"passed_time":0.07775195833,"remaining_time":0.0159250999},
{"learn":[17.77446357],"iteration":83,"passed_time":0.07870104167,"remaining_time":0.0149906746},
{"learn":[17.71083994],"iteration":84,"passed_time":0.07970925,"remaining_time":0.01406633824},
{"learn":[17.60793492],"iteration":85,"passed_time":0.080688125,"remaining_time":0.01313527616},
{"learn":[17.38958019],"iteration":86,"passed_time":0.08149333333,"remaining_time":0.01217716475},
{"learn":[17.32627137],"iteration":87,"passed_time":0.08238045833,"remaining_time":0.01123369886},
{"learn":[17.21054164],"iteration":88,"passed_time":0.08326629167,"remaining_time":0.01029133942},
{"learn":[17.04451092],"iteration":89,"passed_time":0.08406779167,"remaining_time":0.009340865741},
{"learn":[16.87720621],"iteration":90,"passed_time":0.08521291667,"remaining_time":0.008427651099},
{"learn":[16.81305119],"iteration":91,"passed_time":0.08613433333,"remaining_time":0.007489942029},
{"learn":[16.71467153],"iteration":92,"passed_time":0.08704841667,"remaining_time":0.006552031362},
{"learn":[16.55498805],"iteration":93,"passed_time":0.08790858333,"remaining_time":0.00561118617},
{"learn":[16.31618223],"iteration":94,"passed_time":0.08899783333,"remaining_time":0.004684096491},
{"learn":[16.26529169],"iteration":95,"passed_time":0.09000591667,"remaining_time":0.003750246528},
{"learn":[16.08978302],"iteration":96,"passed_time":0.090829875,"remaining_time":0.002809171392},
{"learn":[15.96674128],"iteration":97,"passed_time":0.09185583333,"remaining_time":0.001874608844},
{"learn":[15.76576954],"iteration":98,"passed_time":0.09271545833,"remaining_time":0.0009365197811},
{"learn":[15.73502701],"iteration":99,"passed_time":0.093510625,"remaining_time":0}
]}